slicerutil/__init__.py
slicerutil/basic_functions.py
slicerutil/image_volume.py
slicerutil/segment.py
slicerutil/segmentation_node.py
slicerutil/utils.py
slicerutil/assets/Banner.png
slicerutil/assets/SlicerJupyterScreenCapture.png
slicerutil-0.2.2.dist-info/LICENSE
slicerutil-0.2.2.dist-info/METADATA
slicerutil-0.2.2.dist-info/WHEEL
slicerutil-0.2.2.dist-info/top_level.txt
slicerutil-0.2.2.dist-info/RECORD
