Metadata-Version: 2.1
Name: slicerutil
Version: 0.2.2
Summary: A package created for ease of use working with NumPy in 3D Slicer
Home-page: https://github.com/Marcus-Milantoni/Slicer_Utility
Author: Marcus Milantoni
Author-email: mmilanto@uwo.ca
License: MIT
Keywords: 3D slicer,Utility,Image Processing,NumPy
Classifier: Programming Language :: Python :: 3
Classifier: License :: OSI Approved :: MIT License
Classifier: Operating System :: OS Independent
Classifier: Topic :: Scientific/Engineering :: Medical Science Apps.
Classifier: Topic :: Scientific/Engineering :: Image Processing
Classifier: Topic :: Scientific/Engineering :: Physics
Requires-Python: >=3.6
License-File: LICENSE
Requires-Dist: numpy
Requires-Dist: matplotlib
